torchqc/adams_bashforth_methods.py
torchqc/common_functions.py
torchqc/common_matrices.py
torchqc/correlation.py
torchqc/dynamics.py
torchqc/fock_liouville.py
torchqc/mappings.py
torchqc/markovian.py
torchqc/operators.py
torchqc/runge_kutta_methods.py
torchqc/spin.py
torchqc/states.py
torchqc/tensor_product.py
torchqc-1.3.0.dist-info/licenses/LICENSE
torchqc-1.3.0.dist-info/METADATA
torchqc-1.3.0.dist-info/WHEEL
torchqc-1.3.0.dist-info/top_level.txt
torchqc-1.3.0.dist-info/RECORD
