Metadata-Version: 2.4
Name: torchqc
Version: 1.3.0
Summary: Quantum simulation library based on PyTorch
Author: Dimitris Koutromanos
Author-email: Dimitris Koutromanos <dkoutromanos@upatras.gr>
Project-URL: Homepage, https://github.com/qoptics-qtech/torchqc
Classifier: Programming Language :: Python :: 3
Classifier: License :: OSI Approved :: MIT License
Classifier: Operating System :: OS Independent
Requires-Python: >=3.8
License-File: LICENSE
Requires-Dist: numpy>=2.0.0
Requires-Dist: torch>=2.3.1
Dynamic: author
Dynamic: license-file
